haunted_mansion/__init__.py
haunted_mansion/game.py
haunted_mansion-1.0.0.dist-info/METADATA
haunted_mansion-1.0.0.dist-info/WHEEL
haunted_mansion-1.0.0.dist-info/entry_points.txt
haunted_mansion-1.0.0.dist-info/top_level.txt
haunted_mansion-1.0.0.dist-info/RECORD
